README.md
mock_protocol.py
setup.py
mock_protocol.egg-info/PKG-INFO
mock_protocol.egg-info/SOURCES.txt
mock_protocol.egg-info/dependency_links.txt
mock_protocol.egg-info/top_level.txt