Metadata-Version: 2.1
Name: mock-protocol
Version: 1.0.0
Summary: A unittest mock library than understands annotations
Home-page: https://github.com/tim-mitchell/mocka
Author: Tim Mitchell
Author-email: tim.mitchell@seequent.com
License: UNKNOWN
Project-URL: Source, https://github.com/tim-mitchell/mocka/
Keywords: test unittest mock protocol annotation
Platform: UNKNOWN
Classifier: Development Status :: 4 - Beta
Classifier: Intended Audience :: Developers
Classifier: Topic :: Software Development :: Testing :: Mocking
Classifier: License :: OSI Approved :: MIT License
Classifier: Programming Language :: Python :: 3
Classifier: Programming Language :: Python :: 3.6
Classifier: Programming Language :: Python :: 3.7
Classifier: Programming Language :: Python :: 3.8
Classifier: Programming Language :: Python :: 3.9
Classifier: Programming Language :: Python :: 3 :: Only
Requires-Python: >=3.6, <4
